{"images":["https://tse4.mm.bing.net/th/id/OIG.iQEkY2tDLhqhW_nEsKxE","https://tse2.mm.bing.net/th/id/OIG.cJrxsz6LQP4ZTYmzdywk","https://tse1.mm.bing.net/th/id/OIG.u7fsXku2FWQsHV38_LQr","https://tse2.mm.bing.net/th/id/OIG.pPNSSW6VqJ5MqKMM.qNm"],"content":"Combine the Chinese ancient poem \"Using the Chinese ancient poem \"Inspired by the Chinese ancient poem \"雨后寒轻，风前香软，春在梨花。\", create an oil painting-style artwork that reflects the poetic charm and characters.\" as the source of inspiration, draw a realistic-style picture that highlights the scene details and atmosphere.\" with cyberpunk elements to design a unique image blending tradition and sci-fi.","origin":"柳梢青·吴中","author":"仲殊","category":"古诗文-植物-梨花","date":"2023/11/5 11:40:16","localImagesPath":"1699155616572"}